{
  "BM": "BagMotic",
  "RA": "Rainbow",
  "NN": "Nessuna Collezione",
  "B2": "Blue Square",
  "OM5": "Umbrella",
  "OM6": "Umbrella",
  "AP": "Harper",
  "MOS": "Modus Restyling",
  "B3": "Black Square",
  "ALU": "Collezione Alu",
  "PQL": "Collezione Pq-light",
  "PQLM": "Collezione Pq-light Con Frame",
  "PQLS2": "Pql-special2",
  "BR2": "Brief 2",
  "MO": "Modus",
  "BR": "Brief",
  "P16": "P16",
  "UB00": "Urban",
  "S125": "Arne",
  "W92": "Circle",
  "C2O": "Corner 2.0",
  "B2V": "B2 Revamp",
  "FLD": "Collezione Fld",
  "CY": "Class-ify",
  "C11": "Cinture Coll.11",
  "C81": "Cinture Coll.81",
  "H1": "Caschi Da Moto Coll. 1",
  "AO": "Akron",
  "SI": "Signo",
  "SKR": "Sticker",
  "BIZ": "Collezione Biz",
  "CAS2": "Corno Alle Scale 2",
  "RS": "Collezione Re Start",
  "C2OW": "Corner Spciale Gommato",
  "W129": "Wollem",
  "PQLS3": "Pql-special3",
  "TA": "Packing Cube",
  "BR2S": "Brief 2 Special",
  "ALUM": "Collezione Progetto Maserati",
  "MOSM": "Collezione Modus Maserati",
  "W121": "Titi",
  "ALUB2": "Collezione Alu B2",
  "W134": "Collezione W134",
  "C105": "Cinture Coll.105",
  "C106": "Cinture Coll.106",
  "C107": "Cinture Coll.107",
  "W129W": "Wollem Gommata",
  "J59": "Giacche Coll. J59",
  "C2OWD": "Corner Spciale Gommato",
  "POPD": "Collezione Pq-light",
  "POP": "Collezione Pop",
  "S137": "Collezione S137",
  "S135": "Than",
  "S136": "Orion",
  "S138": "Atlas",
  "W92T": "Lyra",
  "S134": "Cronus",
  "S140": "Collezione S140",
  "C109": "Cinture Coll.109",
  "C108": "Cinture Coll.108",
  "C110": "Cinture Coll 110",
  "RU": "Collezione Scarpe Ru",
  "TE": "Collezione Te"
}